{"cameraMode":{"drawMode":0,"name":"Shaded","section":"Shading Mode"},"sceneLighting":true,"audioPlay":false,"sceneViewState":{"m_AlwaysRefresh":false,"showFog":true,"showSkybox":true,"showFlares":true,"showImageEffects":true,"showParticleSystems":true,"showVisualEffectGraphs":true,"m_FxEnabled":true},"in2DMode":false,"pivot":{"x":36.24835968017578,"y":1.993239402770996,"z":-3.7189388275146486},"rotation":{"x":0.0037589315325021745,"y":0.9961316585540772,"z":-0.054152704775333408,"w":0.06914366036653519},"size":19.57831382751465,"orthographic":false}